02/alu.sv
`define alu 1

module alu(
    input  [15:0] x,
    input  [15:0] y,
    input         zx,
    input         nx,
    input         zy,
    input         ny,
    input         f,
    input         no,
    output [15:0] out,
    output        zr,
    output        ng
);
   
reg [5:0] selector;
reg[15:0] alu_tmp; 

always_comb begin
  selector = {zx, nx, zy, ny, f, no};
end 

always_comb begin
  case (selector)
    6'b101010 : alu_tmp = 16'b0;
    6'b111111 : alu_tmp = 16'b1;
    6'b111010 : alu_tmp = 16'b1111111111111111;
    6'b001100 : alu_tmp = x;
    6'b110000 : alu_tmp = y;
    6'b001101 : alu_tmp = ~x;
    6'b110001 : alu_tmp = ~y;
    6'b001111 : alu_tmp = (~x) + 16'b1;
    6'b110011 : alu_tmp = (~y) + 16'b1;
    6'b011111 : alu_tmp = x + 16'b1;
    6'b110111 : alu_tmp = y + 16'b1;
    6'b001110 : alu_tmp = x - 16'b1;
    6'b110010 : alu_tmp = y - 16'b1;
    6'b000010 : alu_tmp = x + y;
    6'b010011 : alu_tmp = x - y;
    6'b000111 : alu_tmp = y - x;
    6'b000000 : alu_tmp = x & y;
    6'b010101 : alu_tmp = x | y;
    default   : alu_tmp = 16'b0;  
  endcase
end

assign out = alu_tmp;
assign zr = (16'b0 == alu_tmp) ? 1'b1 : 1'b0;
assign ng = alu_tmp[15];

endmodule

05/cpu.sv
`include "../02/alu.sv"

module cpu(
    input  [15:0] inM,
    input  [15:0] instruction,
    input         reset,
    input         clock,
    output [15:0] outM,
    output        loadM,
    output [15:0] addressM,
    output reg [15:0] pc
);
    assign addressM = regA;
    wire loadI;
    wire loadA;
    wire loadD;
    assign outM = outALU;    
    wire [15:0] am;
    assign am = (instruction[12]) ? inM : regA;
    wire lt;
    wire eq;
    wire jmp;
    wire inc;
    wire [15:0] outALU;
        
    reg [15:0] regA;
    reg [15:0] regD;
    alu ALU_0(
        .x(regD),
        .y(am),
        .zx(instruction[11]),
        .nx(instruction[10]),
        .zy(instruction[9]),
        .ny(instruction[8]),
        .f(instruction[7]),
        .no(instruction[6]),
        .out(outALU),
        .zr(eq),
        .ng(lt)
    );
    
    assign loadI = ~instruction[15];
    assign loadA = instruction[15] & instruction[5];
    assign loadD = instruction[15] & instruction[4];
    assign loadM = instruction[15] & instruction[3];
    assign jmp = instruction[15] & ((lt & instruction[2]) | (eq & instruction[1]) | ((!(lt|eq)) & instruction[0]));
    
    always @(posedge clock)
        if (reset) pc <= 0;
        else if (jmp) pc <= regA;
        else pc <= pc+1;

    always @(posedge clock)
        if (reset) regA <= 0;
        else if (loadI) regA <= instruction;
        else if (loadA) regA <= outALU;
        else regA <= regA;
    
    always @(posedge clock)
        if (reset) regD <= 0;
        else if (loadD) regD <= outALU;
        else regD <= regD;

endmodule

05/CPU_mine_tb.sv
`default_nettype none
`include "cpu.sv"

module CPU_tb();

    integer file;
    reg clk=0;    
    reg [15:0] inM=0;
    reg [15:0] instruction=0;
    reg reset=1;
    wire [15:0] outM;
    wire loadM;
    wire [15:0] addressM;
    wire [15:0] pc;
    cpu CPU(
        .clock(clk),
        .inM(inM),
        .instruction(instruction),
        .reset(reset),
        .outM(outM),
        .loadM(loadM),
        .addressM(addressM),
        .pc(pc)
    );

    always #1 clk = ~clk;

    task display;
        #1 $fwrite(file, "| %16b | %16b | %16b | %1b | %16b | %1b | %16b |\n",pc,inM,instruction,reset,outM,loadM,addressM);
    endtask

    initial begin
        $dumpfile("CPU_tb.vcd");
        $dumpvars(0, CPU_tb);
        file = $fopen("CPU.out","w");
        $fwrite(file, "|       pc         |       inM        |    instruction   |rst|       outM       |wM |    addressM      |\n");

        #1 reset = 1;
        display();
        #1 reset = 0;
        display();
        #2 instruction = 16'b0011000000111001; // @12345
        display();

        #2 instruction = 16'b1110110000010000; // D=A
        display();

        #2 instruction = 16'b0101101110100000; // @23456
        display();

        #2 instruction = 16'b1110000111010000; // D=A-D
        display();

        #2 instruction = 16'b0000001111101000; // @1000
        display();

        #2 instruction = 16'b1110001100001000; // M=D
        display();

        #2 instruction = 16'b0000001111101001; // @1001
        display();

        #2 instruction = 16'b1110001110011000; // MD=D-1
        display();

        #2 instruction = 16'b0000001111101000; // @1000
        display();

        #2 instruction = 16'b1111010011010000; // D=D-M
        #2 inM=11111;
        display();

        #2 instruction = 16'b0000000000001110; // @14
        display();

        #2 instruction = 16'b1110001100000100; // D;jlt
        display();

        #2 instruction = 16'b0000001111100111; // @999
        display();

        #2 instruction = 16'b1110110111100000; // A=A+1
        display();

        #2 instruction = 16'b1110001100001000; // M=D
        display();

        #2 instruction = 16'b0000000000010101; // @21
        display();

        #2 instruction = 16'b1110011111000010; // D+1;jeq
        display();

        #2 instruction = 16'b0000000000000010; // @2
        display();

        #2 instruction = 16'b1110000010010000; // D=D+A
        display();

        #2 instruction = 16'b0000001111101000; // @1000
        display();

        #2 instruction = 16'b1110111010010000; // D=-1
        display();

        #2 instruction = 16'b1110001100000001; // D;JGT
        display();

        #2 instruction = 16'b1110001100000010; // D;JEQ
        display();

        #2 instruction = 16'b1110001100000011; // D;JGE
        display();

        #2 instruction = 16'b1110001100000100; // D;JLT
        display();

        #2 instruction = 16'b1110001100000101; // D;JNE
        display();

        #2 instruction = 16'b1110001100000110; // D;JLE
        display();

        #2 instruction = 16'b1110001100000111; // D;JMP
        display();

        #2 instruction = 16'b1110101010010000; // D=0
        display();

        #2 instruction = 16'b1110001100000001; // D;JGT
        display();

        #2 instruction = 16'b1110001100000010; // D;JEQ
        display();

        #2 instruction = 16'b1110001100000011; // D;JGE
        display();

        #2 instruction = 16'b1110001100000100; // D;JLT
        display();

        #2 instruction = 16'b1110001100000101; // D;JNE
        display();

        #2 instruction = 16'b1110001100000110; // D;JLE
        display();

        #2 instruction = 16'b1110001100000111; // D;JMP
        display();

        #2 instruction = 16'b1110111111010000; // D=1
        display();

        #2 instruction = 16'b1110001100000001; // D;JGT
        display();

        #2 instruction = 16'b1110001100000010; // D;JEQ
        display();

        #2 instruction = 16'b1110001100000011; // D;JGE
        display();

        #2 instruction = 16'b1110001100000100; // D;JLT
        display();

        #2 instruction = 16'b1110001100000101; // D;JNE
        display();

        #2 instruction = 16'b1110001100000110; // D;JLE
        display();

        #2 instruction = 16'b1110001100000111; // D;JMP
        display();

        #2 reset=1;
        display();

        #2 instruction = 16'b0111111111111111; // @32767
        #2 reset=0;
        display();

        $finish;
	end

endmodule

build/CPU_tb.vcd
$date
	Thu Mar 13 23:25:03 2025
$end
$version
	Icarus Verilog
$end
$timescale
	1s
$end
$scope module CPU_tb $end
$var wire 16 ! pc [15:0] $end
$var wire 16 " outM [15:0] $end
$var wire 1 # loadM $end
$var wire 16 $ addressM [15:0] $end
$var reg 1 % clk $end
$var reg 16 & inM [15:0] $end
$var reg 16 ' instruction [15:0] $end
$var reg 1 ( reset $end
$var integer 32 ) file [31:0] $end
$scope module CPU $end
$var wire 16 * addressM [15:0] $end
$var wire 1 % clock $end
$var wire 16 + inM [15:0] $end
$var wire 16 , instruction [15:0] $end
$var wire 1 - jmp $end
$var wire 1 . loadA $end
$var wire 1 / loadD $end
$var wire 1 0 loadI $end
$var wire 1 # loadM $end
$var wire 16 1 outM [15:0] $end
$var wire 1 ( reset $end
$var wire 16 2 outALU [15:0] $end
$var wire 1 3 lt $end
$var wire 1 4 eq $end
$var wire 16 5 am [15:0] $end
$var reg 16 6 pc [15:0] $end
$var reg 16 7 regA [15:0] $end
$var reg 16 8 regD [15:0] $end
$scope module ALU_0 $end
$var wire 1 9 f $end
$var wire 1 : no $end
$var wire 1 ; nx $end
$var wire 1 < ny $end
$var wire 16 = out [15:0] $end
$var wire 16 > x [15:0] $end
$var wire 16 ? y [15:0] $end
$var wire 1 @ zx $end
$var wire 1 A zy $end
$var wire 1 4 zr $end
$var wire 1 3 ng $end
$var reg 16 B alu_tmp [15:0] $end
$var reg 6 C selector [5:0] $end
$upscope $end
$upscope $end
$scope task display $end
$upscope $end
$upscope $end
$enddefinitions $end
#0
$dumpvars
b0 C
bx B
0A
0@
bx ?
bx >
bx =
0<
0;
0:
09
bx 8
bx 7
bx 6
bx 5
x4
x3
bx 2
bx 1
10
0/
0.
0-
b0 ,
b0 +
bx *
b10000000000000000000000000000011 )
1(
b0 '
b0 &
0%
bx $
0#
bx "
bx !
$end
#1
14
03
b0 5
b0 ?
b0 "
b0 1
b0 2
b0 =
b0 B
b0 !
b0 6
b0 $
b0 *
b0 7
b0 8
b0 >
1%
#2
0%
#3
b1 !
b1 6
0(
1%
#4
0%
#5
b10 !
b10 6
1%
#6
0%
b11000000111001 '
b11000000111001 ,
#7
b11000000111001 $
b11000000111001 *
b11000000111001 7
b11 !
b11 6
1%
#8
0%
#9
13
b100 !
b100 6
b1110110000010000 $
b1110110000010000 *
b1110110000010000 7
04
b1110110000010000 "
b1110110000010000 1
b1110110000010000 2
b1110110000010000 =
b1110110000010000 B
b1110110000010000 5
b1110110000010000 ?
b110000 C
00
1/
1@
1;
1%
b1110110000010000 '
b1110110000010000 ,
#10
0%
#11
b1110110000010000 8
b1110110000010000 >
b101 !
b101 6
1%
#12
14
03
b0 "
b0 1
b0 2
b0 =
b0 B
b0 5
b0 ?
b101110 C
10
0/
0;
1A
1<
19
0%
b101101110100000 '
b101101110100000 ,
#13
b110 !
b110 6
b101101110100000 $
b101101110100000 *
b101101110100000 7
1%
#14
0%
#15
13
b1110000111010000 $
b1110000111010000 *
b1110000111010000 7
b111 !
b111 6
04
b1111010111000000 "
b1111010111000000 1
b1111010111000000 2
b1111010111000000 =
b1111010111000000 B
b1110000111010000 5
b1110000111010000 ?
b111 C
00
1/
0@
0A
1:
1%
b1110000111010000 '
b1110000111010000 ,
#16
0%
#17
b1110110000010000 "
b1110110000010000 1
b1110110000010000 2
b1110110000010000 =
b1110110000010000 B
b1000 !
b1000 6
b1111010111000000 8
b1111010111000000 >
1%
#18
03
b101001000000 "
b101001000000 1
b101001000000 2
b101001000000 =
b101001000000 B
b1111 C
10
0/
1A
0%
b1111101000 '
b1111101000 ,
#19
b1111101000 5
b1111101000 ?
b1111101000 $
b1111101000 *
b1111101000 7
b1001 !
b1001 6
1%
#20
0%
#21
b1110001100001000 5
b1110001100001000 ?
b1010 !
b1010 6
b1110001100001000 $
b1110001100001000 *
b1110001100001000 7
13
b1111010111000000 "
b1111010111000000 1
b1111010111000000 2
b1111010111000000 =
b1111010111000000 B
b1100 C
00
1#
09
0:
1%
b1110001100001000 '
b1110001100001000 ,
#22
0%
#23
b1011 !
b1011 6
1%
#24
03
b101001000000 "
b101001000000 1
b101001000000 2
b101001000000 =
b101001000000 B
b1111 C
10
0#
19
1:
0%
b1111101001 '
b1111101001 ,
#25
b1111101001 5
b1111101001 ?
b1100 !
b1100 6
b1111101001 $
b1111101001 *
b1111101001 7
1%
#26
0%
#27
b1110001110011000 5
b1110001110011000 ?
b1110001110011000 $
b1110001110011000 *
b1110001110011000 7
b1101 !
b1101 6
13
b1111010110111111 "
b1111010110111111 1
b1111010110111111 2
b1111010110111111 =
b1111010110111111 B
b1110 C
00
1/
1#
0-
0:
1%
b1110001110011000 '
b1110001110011000 ,
#28
0%
#29
b1111010110111110 "
b1111010110111110 1
b1111010110111110 2
b1111010110111110 =
b1111010110111110 B
b1110 !
b1110 6
b1111010110111111 8
b1111010110111111 >
1%
#30
03
b101001000001 "
b101001000001 1
b101001000001 2
b101001000001 =
b101001000001 B
b1111 C
10
0/
0#
1:
0%
b1111101000 '
b1111101000 ,
#31
b1111101000 5
b1111101000 ?
b1111101000 $
b1111101000 *
b1111101000 7
b1111 !
b1111 6
1%
#32
0%
#33
b10000 !
b10000 6
b1111010011010000 $
b1111010011010000 *
b1111010011010000 7
13
b1111010110111111 "
b1111010110111111 1
b1111010110111111 2
b1111010110111111 =
b1111010110111111 B
b0 5
b0 ?
b10011 C
00
1/
1;
0A
0<
1%
b1111010011010000 '
b1111010011010000 ,
#34
0%
#35
b10001 !
b10001 6
b1100101001011000 "
b1100101001011000 1
b1100101001011000 2
b1100101001011000 =
b1100101001011000 B
b10101101100111 5
b10101101100111 ?
1%
b10101101100111 &
b10101101100111 +
#36
0%
#37
b1001111011110001 "
b1001111011110001 1
b1001111011110001 2
b1001111011110001 =
b1001111011110001 B
b10010 !
b10010 6
b1100101001011000 8
b1100101001011000 >
1%
#38
b1100000001010000 "
b1100000001010000 1
b1100000001010000 2
b1100000001010000 =
b1100000001010000 B
b1111010011010000 5
b1111010011010000 ?
b0 C
10
0/
0;
09
0:
0%
b1110 '
b1110 ,
#39
03
b1000 "
b1000 1
b1000 2
b1000 =
b1000 B
b1110 5
b1110 ?
b1110 $
b1110 *
b1110 7
b10011 !
b10011 6
1%
#40
0%
#41
b1110001100000100 5
b1110001100000100 ?
b10100 !
b10100 6
b1110001100000100 $
b1110001100000100 *
b1110001100000100 7
1-
13
b1100101001011000 "
b1100101001011000 1
b1100101001011000 2
b1100101001011000 =
b1100101001011000 B
b1100 C
00
1A
1<
1%
b1110001100000100 '
b1110001100000100 ,
#42
0%
#43
b1110001100000100 !
b1110001100000100 6
1%
#44
03
b11010110101000 "
b11010110101000 1
b11010110101000 2
b11010110101000 =
b11010110101000 B
b1111 C
10
0-
19
1:
0%
b1111100111 '
b1111100111 ,
#45
b1111100111 5
b1111100111 ?
b1110001100000101 !
b1110001100000101 6
b1111100111 $
b1111100111 *
b1111100111 7
1%
#46
0%
#47
13
b1110110111100000 5
b1110110111100000 ?
b1110110111100000 $
b1110110111100000 *
b1110110111100000 7
b1110001100000110 !
b1110001100000110 6
b1110110111100001 "
b1110110111100001 1
b1110110111100001 2
b1110110111100001 =
b1110110111100001 B
b110111 C
00
1.
0-
1@
1;
0A
1%
b1110110111100000 '
b1110110111100000 ,
#48
0%
#49
b1110110111100010 "
b1110110111100010 1
b1110110111100010 2
b1110110111100010 =
b1110110111100010 B
b1110110111100001 5
b1110110111100001 ?
b1110001100000111 !
b1110001100000111 6
b1110110111100001 $
b1110110111100001 *
b1110110111100001 7
1%
#50
b1100101001011000 "
b1100101001011000 1
b1100101001011000 2
b1100101001011000 =
b1100101001011000 B
b1100 C
0.
1#
0@
0;
1A
09
0:
0%
b1110001100001000 '
b1110001100001000 ,
#51
b1110001100001000 !
b1110001100001000 6
1%
#52
0%
#53
b1110001100001001 !
b1110001100001001 6
b1100100001000000 "
b1100100001000000 1
b1100100001000000 2
b1100100001000000 =
b1100100001000000 B
b0 C
10
0#
0A
0<
1%
b10101 '
b10101 ,
#54
0%
#55
03
b10000 "
b10000 1
b10000 2
b10000 =
b10000 B
b10101 5
b10101 ?
b10101 $
b10101 *
b10101 7
b1110001100001010 !
b1110001100001010 6
1%
#56
13
b1100101001011001 "
b1100101001011001 1
b1100101001011001 2
b1100101001011001 =
b1100101001011001 B
b11111 C
00
0-
1;
1A
1<
19
1:
0%
b1110011111000010 '
b1110011111000010 ,
#57
b1110001100001011 !
b1110001100001011 6
1%
#58
0%
#59
b1110001100001100 !
b1110001100001100 6
03
b10000 "
b10000 1
b10000 2
b10000 =
b10000 B
b0 C
10
0;
0A
0<
09
0:
1%
b10 '
b10 ,
#60
0%
#61
14
b0 "
b0 1
b0 2
b0 =
b0 B
b10 5
b10 ?
b1110001100001101 !
b1110001100001101 6
b10 $
b10 *
b10 7
1%
#62
04
13
b1100101001011010 "
b1100101001011010 1
b1100101001011010 2
b1100101001011010 =
b1100101001011010 B
b10 C
00
1/
0-
19
0%
b1110000010010000 '
b1110000010010000 ,
#63
b1100101001011100 "
b1100101001011100 1
b1100101001011100 2
b1100101001011100 =
b1100101001011100 B
b1100101001011010 8
b1100101001011010 >
b1110001100001110 !
b1110001100001110 6
1%
#64
0%
#65
b1110001100001111 !
b1110001100001111 6
b1100101001011100 8
b1100101001011100 >
03
b11010110100100 "
b11010110100100 1
b11010110100100 2
b11010110100100 =
b11010110100100 B
b1111 C
10
0/
1A
1<
1:
1%
b1111101000 '
b1111101000 ,
#66
0%
#67
b1111101000 5
b1111101000 ?
b1111101000 $
b1111101000 *
b1111101000 7
b1110001100010000 !
b1110001100010000 6
1%
#68
13
b1111111111111111 "
b1111111111111111 1
b1111111111111111 2
b1111111111111111 =
b1111111111111111 B
b111010 C
00
1/
1@
1;
0<
0:
0%
b1110111010010000 '
b1110111010010000 ,
#69
b1110001100010001 !
b1110001100010001 6
b1111111111111111 8
b1111111111111111 >
1%
#70
0%
#71
b1110001100010010 !
b1110001100010010 6
b1100 C
0/
0@
0;
1<
09
1%
b1110001100000001 '
b1110001100000001 ,
#72
0%
#73
b1110001100010011 !
b1110001100010011 6
1%
#74
0%
b1110001100000010 '
b1110001100000010 ,
#75
b1110001100010100 !
b1110001100010100 6
1%
#76
0%
#77
b1110001100010101 !
b1110001100010101 6
1%
b1110001100000011 '
b1110001100000011 ,
#78
0%
#79
b1110001100010110 !
b1110001100010110 6
1%
#80
1-
0%
b1110001100000100 '
b1110001100000100 ,
#81
b1111101000 !
b1111101000 6
1%
#82
0%
#83
1%
b1110001100000101 '
b1110001100000101 ,
#84
0%
#85
1%
#86
0%
b1110001100000110 '
b1110001100000110 ,
#87
1%
#88
0%
#89
1%
b1110001100000111 '
b1110001100000111 ,
#90
0%
#91
1%
#92
0-
14
03
b0 "
b0 1
b0 2
b0 =
b0 B
b101010 C
1/
1@
0<
19
0%
b1110101010010000 '
b1110101010010000 ,
#93
b1111101001 !
b1111101001 6
b0 8
b0 >
1%
#94
0%
#95
b1111101010 !
b1111101010 6
b1100 C
0/
0@
1<
09
1%
b1110001100000001 '
b1110001100000001 ,
#96
0%
#97
b1111101011 !
b1111101011 6
1%
#98
1-
0%
b1110001100000010 '
b1110001100000010 ,
#99
b1111101000 !
b1111101000 6
1%
#100
0%
#101
1%
b1110001100000011 '
b1110001100000011 ,
#102
0%
#103
1%
#104
0-
0%
b1110001100000100 '
b1110001100000100 ,
#105
b1111101001 !
b1111101001 6
1%
#106
0%
#107
b1111101010 !
b1111101010 6
1%
b1110001100000101 '
b1110001100000101 ,
#108
0%
#109
b1111101011 !
b1111101011 6
1%
#110
1-
0%
b1110001100000110 '
b1110001100000110 ,
#111
b1111101000 !
b1111101000 6
1%
#112
0%
#113
1%
b1110001100000111 '
b1110001100000111 ,
#114
0%
#115
1%
#116
0-
04
b1 "
b1 1
b1 2
b1 =
b1 B
b111111 C
1/
1@
1;
19
1:
0%
b1110111111010000 '
b1110111111010000 ,
#117
b1111101001 !
b1111101001 6
b1 8
b1 >
1%
#118
0%
#119
b1111101010 !
b1111101010 6
1-
b1100 C
0/
0@
0;
09
0:
1%
b1110001100000001 '
b1110001100000001 ,
#120
0%
#121
b1111101000 !
b1111101000 6
1%
#122
0-
0%
b1110001100000010 '
b1110001100000010 ,
#123
b1111101001 !
b1111101001 6
1%
#124
0%
#125
b1111101010 !
b1111101010 6
1-
1%
b1110001100000011 '
b1110001100000011 ,
#126
0%
#127
b1111101000 !
b1111101000 6
1%
#128
0-
0%
b1110001100000100 '
b1110001100000100 ,
#129
b1111101001 !
b1111101001 6
1%
#130
0%
#131
b1111101010 !
b1111101010 6
1-
1%
b1110001100000101 '
b1110001100000101 ,
#132
0%
#133
b1111101000 !
b1111101000 6
1%
#134
0-
0%
b1110001100000110 '
b1110001100000110 ,
#135
b1111101001 !
b1111101001 6
1%
#136
0%
#137
b1111101010 !
b1111101010 6
1-
1%
b1110001100000111 '
b1110001100000111 ,
#138
0%
#139
b1111101000 !
b1111101000 6
1%
#140
0%
1(
#141
14
b0 5
b0 ?
b0 "
b0 1
b0 2
b0 =
b0 B
b0 !
b0 6
b0 $
b0 *
b0 7
b0 8
b0 >
1%
#142
0%
#143
04
b1 "
b1 1
b1 2
b1 =
b1 B
b10101101100111 5
b10101101100111 ?
b111111 C
10
0-
1@
1;
19
1:
1%
b111111111111111 '
b111111111111111 ,
#144
0%
#145
b1 !
b1 6
b111111111111111 $
b111111111111111 *
b111111111111111 7
1%
0(
